[{
  "startStop": "A",
  "endStop": "B",
  "speedLimit": 100,
  "legID": "AB"
  },
  {
  "startStop": "B",
  "endStop": "C",
  "speedLimit": 60,
  "legID": "BC"},
  {
  "startStop": "C",
  "endStop": "D",
  "speedLimit": 80,
  "legID": "CD"
  },
  {
  "startStop": "D",
  "endStop": "E",
  "speedLimit": 120,
  "legID": "DE"
  },
  {
  "startStop": "E",
  "endStop": "F",
  "speedLimit": 40,
  "legID": "EF"
  },
  {
  "startStop": "F",
  "endStop": "G",
  "speedLimit": 40,
  "legID": "FG"
  },
  {
  "startStop": "G",
  "endStop": "H",
  "speedLimit": 100,
  "legID": "GH"
  },
  {
  "startStop": "H",
  "endStop": "I",
  "speedLimit": 100,
  "legID": "HI"
  },
  {
  "startStop": "I",
  "endStop": "J",
  "speedLimit": 50,
  "legID": "IJ"
  },
  {
  "startStop": "J",
  "endStop": "K",
  "speedLimit": 100,
  "legID": "JK"
  },
  {
  "startStop": "K",
  "endStop": "L",
  "speedLimit": 60,"legID": "KL"
  }
  ]